olympia/__init__.py
olympia/linked_list.py
olympia/py.typed
olympia-0.2.0.dist-info/entry_points.txt
olympia-0.2.0.dist-info/LICENSE
olympia-0.2.0.dist-info/WHEEL
olympia-0.2.0.dist-info/METADATA
olympia-0.2.0.dist-info/RECORD
