Metadata-Version: 2.1
Name: olympia
Version: 0.2.0
Summary: Olympia
Home-page: https://github.com/lukemiloszewski/olympia
License: MIT
Author: Luke Miloszewski
Author-email: lukemiloszewski@gmail.com
Requires-Python: >=3.7.1,<4.0.0
Classifier: Intended Audience :: Developers
Classifier: License :: OSI Approved :: MIT License
Classifier: Operating System :: OS Independent
Classifier: Programming Language :: Python :: 3
Classifier: Programming Language :: Python :: 3 :: Only
Classifier: Programming Language :: Python :: 3.10
Classifier: Programming Language :: Python :: 3.7
Classifier: Programming Language :: Python :: 3.8
Classifier: Programming Language :: Python :: 3.9
Classifier: Topic :: Software Development
Classifier: Typing :: Typed
Project-URL: Repository, https://github.com/lukemiloszewski/olympia
